correctiv_auth/__init__.py
correctiv_auth/models.py
correctiv_auth/provider.py
correctiv_auth/tests.py
correctiv_auth/urls.py
correctiv_auth/views.py
django_allauth_correctiv-0.0.2.dist-info/DESCRIPTION.rst
django_allauth_correctiv-0.0.2.dist-info/METADATA
django_allauth_correctiv-0.0.2.dist-info/metadata.json
django_allauth_correctiv-0.0.2.dist-info/pbr.json
django_allauth_correctiv-0.0.2.dist-info/RECORD
django_allauth_correctiv-0.0.2.dist-info/top_level.txt
django_allauth_correctiv-0.0.2.dist-info/WHEEL
