Metadata-Version: 2.0
Name: django-allauth-correctiv
Version: 0.0.2
Summary: Django applications addressing authentication with Correctiv.org as a django-allauth module
Home-page: http://github.com/correctiv/django-allauth-correctiv
Author: Stefan Wehrmeyer
Author-email: stefan.wehrmeyer@correctiv.org
License: UNKNOWN
Keywords: django auth account social oauth correctiv registration
Platform: UNKNOWN
Classifier: Development Status :: 4 - Beta
Classifier: Intended Audience :: Developers
Classifier: Topic :: Software Development :: Libraries :: Python Modules
Classifier: Environment :: Web Environment
Classifier: Topic :: Internet
Classifier: License :: OSI Approved :: MIT License
Classifier: Operating System :: OS Independent
Classifier: Programming Language :: Python
Classifier: Programming Language :: Python :: 2.6
Classifier: Programming Language :: Python :: 2.7
Classifier: Programming Language :: Python :: 3.3
Classifier: Programming Language :: Python :: 3.4
Classifier: Framework :: Django
Requires-Dist: django-allauth
